adminlte_base/__init__.py
adminlte_base/constants.py
adminlte_base/data_types.py
adminlte_base/decorators.py
adminlte_base/exceptions.py
adminlte_base/filters.py
adminlte_base/i18n.py
adminlte_base/mixins.py
adminlte_base/contrib/__init__.py
adminlte_base/contrib/forms.py
adminlte_base/contrib/ponyorm.py
adminlte_base/contrib/sqla.py
adminlte_base/templates/adminlte_full/base.html
adminlte_base/templates/adminlte_full/change_password.html
adminlte_base/templates/adminlte_full/forgot_password.html
adminlte_base/templates/adminlte_full/http_error_page.html
adminlte_base/templates/adminlte_full/lockscreen.html
adminlte_base/templates/adminlte_full/login.html
adminlte_base/templates/adminlte_full/recover_password.html
adminlte_base/templates/adminlte_full/register.html
adminlte_base/templates/adminlte_full/search_results.html
adminlte_base/templates/adminlte_full/skeleton.html
adminlte_base/templates/adminlte_full/skeleton_login.html
adminlte_base/templates/adminlte_full/includes/brand_logo.html
adminlte_base/templates/adminlte_full/includes/legacy_user_dropdown.html
adminlte_base/templates/adminlte_full/includes/user_sidebar_panel.html
adminlte_base/templates/adminlte_full/macros/bootstrap4.html
adminlte_base/templates/adminlte_full/macros/markup.html
adminlte_base/templates/adminlte_full/macros/widgets.html
adminlte_base/translations/adminlte_full.pot
adminlte_base/translations/ru/LC_MESSAGES/adminlte_full.mo
adminlte_base/translations/ru/LC_MESSAGES/adminlte_full.po
adminlte_base-0.2.0.dist-info/LICENSE
adminlte_base-0.2.0.dist-info/METADATA
adminlte_base-0.2.0.dist-info/WHEEL
adminlte_base-0.2.0.dist-info/top_level.txt
adminlte_base-0.2.0.dist-info/RECORD
